letmedoit/README.md
letmedoit/config.py
letmedoit/main.py
letmedoit/package_name.txt
letmedoit/requirements.txt
letmedoit-3.0.4.dist-info/METADATA
letmedoit-3.0.4.dist-info/WHEEL
letmedoit-3.0.4.dist-info/entry_points.txt
letmedoit-3.0.4.dist-info/top_level.txt
letmedoit-3.0.4.dist-info/RECORD
