Metadata-Version: 2.1
Name: letmedoit
Version: 3.0.4
Summary: LetMeDoIt AI, an advanced AI assistant, leveraging the capabilities of AI models, to resolve daily tasks for you.
Home-page: https://letmedoit.ai
Author: Eliran Wong
Author-email: support@letmedoit.ai
License: GNU General Public License (GPL)
Project-URL: Source, https://github.com/eliranwong/letmedoit
Project-URL: Tracker, https://github.com/eliranwong/letmedoit/issues
Project-URL: Documentation, https://github.com/eliranwong/letmedoit/wiki
Project-URL: Funding, https://www.paypal.me/letmedoitai
Keywords: ai assistant openai chatgpt gemini autogen rag interpreter auto-heal
Classifier: Development Status :: 5 - Production/Stable
Classifier: Intended Audience :: End Users/Desktop
Classifier: Topic :: Utilities
Classifier: Topic :: Scientific/Engineering :: Artificial Intelligence
Classifier: Topic :: Software Development :: Build Tools
Classifier: License :: OSI Approved :: GNU General Public License v3 or later (GPLv3+)
Classifier: Programming Language :: Python :: 3.8
Classifier: Programming Language :: Python :: 3.9
Classifier: Programming Language :: Python :: 3.10
Classifier: Programming Language :: Python :: 3.11
Classifier: Programming Language :: Python :: 3.12
Requires-Python: >=3.8, <3.13
Requires-Dist: agentmake>=1.0.14
Provides-Extra: genai
Requires-Dist: google-genai>=1.1.0; extra == "genai"
